Bain_Crosspen/__init__.py
Bain_Crosspen/symmetrical_matrix.py
symmetrical_matrix-0.2.dist-info/METADATA
symmetrical_matrix-0.2.dist-info/WHEEL
symmetrical_matrix-0.2.dist-info/top_level.txt
symmetrical_matrix-0.2.dist-info/RECORD
