Metadata-Version: 2.1
Name: symmetrical_matrix
Version: 0.2
Requires-Dist: pandas
